locomotif/locomotif.py
locomotif/old.py
locomotif/scapeplot.py
locomotif/util.py
locomotif/visualize.py
dtai_locomotif-0.1.0.dist-info/LICENSE
dtai_locomotif-0.1.0.dist-info/METADATA
dtai_locomotif-0.1.0.dist-info/WHEEL
dtai_locomotif-0.1.0.dist-info/top_level.txt
dtai_locomotif-0.1.0.dist-info/RECORD
