Metadata-Version: 2.1
Name: dtai-locomotif
Version: 0.1.0
Summary: Discovering variable-length motif sets in multivariate time series using time warping
Home-page: https://github.com/daanvw/locomotif
Author: Daan Van Wesenbeeck
Author-email: daan.vanwesenbeeck@kuleuven.be
License: MIT License
Keywords: time series,motif sets,variable-length,time warping,multivariate
Classifier: License :: OSI Approved :: MIT License
Classifier: Programming Language :: Python
Classifier: Programming Language :: Python :: 3
Requires-Python: >=3.8
License-File: LICENSE
Requires-Dist: numba >=0.30.0
Requires-Dist: matplotlib <4.0,>=3.0
